agora_signaling_sdk-1.0.2.dist-info/DESCRIPTION.rst
agora_signaling_sdk-1.0.2.dist-info/METADATA
agora_signaling_sdk-1.0.2.dist-info/RECORD
agora_signaling_sdk-1.0.2.dist-info/WHEEL
agora_signaling_sdk-1.0.2.dist-info/metadata.json
agora_signaling_sdk-1.0.2.dist-info/top_level.txt
agorasigsdk/__init__.py
agorasigsdk/agora_signal.py
agorasigsdk/call.py
agorasigsdk/channel.py
agorasigsdk/channel2.py
agorasigsdk/login_session.py
agorasigsdk/login_session_state.py
agorasigsdk/message_details.py
agorasigsdk/rpc.py
agorasigsdk/server_address.py
agorasigsdk/signal_consts.py
agorasigsdk/web2_lbs.py
agorasigsdk/websocket_client.py
