Metadata-Version: 2.0
Name: agora-signaling-sdk
Version: 1.0.2
Summary: Agora Signaling Python SDK
Home-page: https://agora.io
Author: Chester@Agora
Author-email: UNKNOWN
License: MIT
Keywords: Agora Signaling SDK
Platform: UNKNOWN
Classifier: Development Status :: 3 - Alpha
Classifier: Intended Audience :: Developers
Classifier: Topic :: Software Development :: Build Tools
Classifier: License :: OSI Approved :: MIT License
Classifier: Programming Language :: Python :: 2
Classifier: Programming Language :: Python :: 2.7
Classifier: Programming Language :: Python :: 3
Classifier: Programming Language :: Python :: 3.3
Classifier: Programming Language :: Python :: 3.4
Classifier: Programming Language :: Python :: 3.5
Classifier: Programming Language :: Python :: 3.6
Requires-Dist: autobahn
Requires-Dist: requests
Requires-Dist: twisted
